{
  "version": 6,
  "cmakeMinimumRequired": {
    "major": 3,
    "minor": 25,
    "patch": 0
  },
  "configurePresets": [
    {
      "name": "base",
      "hidden": true,
      "binaryDir": "${sourceDir}/build/${presetName}",
      "installDir": "${sourceDir}/install/${presetName}",
      "cacheVariables": {
        "CMAKE_CXX_STANDARD": "20",
        "CMAKE_CXX_STANDARD_REQUIRED": "ON",
        "CMAKE_EXPORT_COMPILE_COMMANDS": "ON",
        "CMAKE_CXX_CPPCHECK": "cppcheck;--enable=warning,performance,portability;--inline-suppr;--suppressions-list=${sourceDir}/cppcheck-suppressions.txt;--error-exitcode=1"
      }
    },
    {
      "name": "ninja",
      "displayName": "Ninja Multi-Config",
      "inherits": "base",
      "binaryDir": "${sourceDir}/build",
      "generator": "Ninja Multi-Config",
      "toolchainFile": "$env{VCPKG_ROOT}/scripts/buildsystems/vcpkg.cmake",
      "cacheVariables": {
        "BUILD_NUMBER": "0",
        "OUTPUT_DIR": "build/${presetName}/bin",
        "CMAKE_MODULE_PATH": "${sourceDir};$env{THIRD_PARTY}/net;$env{THIRD_PARTY}/chromebase;$env{THIRD_PARTY}/iec60870;$env{THIRD_PARTY}/iec61850pp;$env{THIRD_PARTY}/sql;$env{THIRD_PARTY}/OPCFoundation;$env{THIRD_PARTY}/promise.hpp"
      }
    }
  ]
}
