<?xml version="1.0" encoding="utf-8"?>
<uax:ListOfNodeState xmlns:xsi="http://www.w3.org/2001/XMLSchema-instance" xmlns:uax="http://opcfoundation.org/UA/2008/02/Types.xsd">
  <uax:NamespaceUris>
    <uax:NamespaceUri>http://telecontrol.ru/opcua/scada</uax:NamespaceUri>
  </uax:NamespaceUris>
  <Creates xmlns="http://telecontrol.ru/opcua/scada">
    <uax:NodeClass>ReferenceType_32</uax:NodeClass>
    <uax:NodeId>
      <uax:Identifier>ns=1;i=23</uax:Identifier>
    </uax:NodeId>
    <uax:BrowseName>
      <uax:NamespaceIndex>1</uax:NamespaceIndex>
      <uax:Name>Creates</uax:Name>
    </uax:BrowseName>
    <uax:Description>
      <uax:Locale></uax:Locale>
      <uax:Text>Objects of target type can be created inside of the source object.</uax:Text>
    </uax:Description>
    <uax:SuperTypeId>
      <uax:Identifier>i=32</uax:Identifier>
    </uax:SuperTypeId>
    <uax:InverseName>
      <uax:Locale></uax:Locale>
      <uax:Text>CreatableIn</uax:Text>
    </uax:InverseName>
  </Creates>
  <HasPropertyCategory xmlns="http://telecontrol.ru/opcua/scada">
    <uax:NodeClass>ReferenceType_32</uax:NodeClass>
    <uax:NodeId>
      <uax:Identifier>ns=1;i=15028</uax:Identifier>
    </uax:NodeId>
    <uax:BrowseName>
      <uax:NamespaceIndex>1</uax:NamespaceIndex>
      <uax:Name>HasPropertyCategory</uax:Name>
    </uax:BrowseName>
    <uax:Description>
      <uax:Locale></uax:Locale>
      <uax:Text>Property belongs to the property category.</uax:Text>
    </uax:Description>
    <uax:SuperTypeId>
      <uax:Identifier>i=32</uax:Identifier>
    </uax:SuperTypeId>
    <uax:InverseName>
      <uax:Locale></uax:Locale>
      <uax:Text>PropertyCategoryOf</uax:Text>
    </uax:InverseName>
  </HasPropertyCategory>
  <PropertyCategories xmlns="http://telecontrol.ru/opcua/scada">
    <uax:NodeClass>Object_1</uax:NodeClass>
    <uax:NodeId>
      <uax:Identifier>ns=1;i=15029</uax:Identifier>
    </uax:NodeId>
    <uax:BrowseName>
      <uax:NamespaceIndex>1</uax:NamespaceIndex>
      <uax:Name>PropertyCategories</uax:Name>
    </uax:BrowseName>
    <uax:ReferenceTypeId>
      <uax:Identifier>i=47</uax:Identifier>
    </uax:ReferenceTypeId>
    <uax:TypeDefinitionId>
      <uax:Identifier>i=61</uax:Identifier>
    </uax:TypeDefinitionId>
    <uax:NumericId>15029</uax:NumericId>
    <uax:References>
      <uax:Reference>
        <uax:ReferenceTypeId>
          <uax:Identifier>i=35</uax:Identifier>
        </uax:ReferenceTypeId>
        <uax:IsInverse>true</uax:IsInverse>
        <uax:TargetId>
          <uax:Identifier>i=85</uax:Identifier>
        </uax:TargetId>
      </uax:Reference>
    </uax:References>
    <General>
      <uax:NodeClass>Object_1</uax:NodeClass>
      <uax:NodeId>
        <uax:Identifier>ns=1;i=15030</uax:Identifier>
      </uax:NodeId>
      <uax:BrowseName>
        <uax:NamespaceIndex>1</uax:NamespaceIndex>
        <uax:Name>General</uax:Name>
      </uax:BrowseName>
      <uax:ReferenceTypeId>
        <uax:Identifier>i=47</uax:Identifier>
      </uax:ReferenceTypeId>
      <uax:TypeDefinitionId>
        <uax:Identifier>i=58</uax:Identifier>
      </uax:TypeDefinitionId>
      <uax:NumericId>15030</uax:NumericId>
    </General>
  </PropertyCategories>
</uax:ListOfNodeState>